{
  "path": "application\\mothership\\services\\payment\\stripe_gateway.py",
  "size": 7704,
  "language": "Python",
  "lines": 212,
  "non_empty_lines": 183,
  "functions": 2,
  "classes": 1,
  "imports": [
    "__future__",
    "logging",
    "typing",
    "exceptions",
    "models.payment",
    "gateway",
    "stripe"
  ],
  "import_lines": [
    7,
    9,
    10,
    17,
    18,
    19,
    13
  ],
  "complexity_estimate": 22.0,
  "comment_density": 0.009433962264150943,
  "has_docstrings": true,
  "side_effects": []
}